MANIFEST.in
setup.py
dummy_app/__init__.py
dummy_app/admin.py
dummy_app/models.py
dummy_app/tests.py
dummy_app/views.py
suggestions/__init__.py
suggestions/admin.py
suggestions/models.py
suggestions/tests.py
suggestions/urls.py
suggestions/views.py
suggestions.egg-info/PKG-INFO
suggestions.egg-info/SOURCES.txt
suggestions.egg-info/dependency_links.txt
suggestions.egg-info/not-zip-safe
suggestions.egg-info/top_level.txt
suggestions/migrations/0001_initial.py
suggestions/migrations/__init__.py
test_app/__init__.py
test_app/settings.py
test_app/urls.py